brei/__init__.py
brei/async_timer.py
brei/cli.py
brei/construct.py
brei/errors.py
brei/lazy.py
brei/logging.py
brei/program.py
brei/py.typed
brei/result.py
brei/runner.py
brei/task.py
brei/template_strings.py
brei/utility.py
brei/version.py
brei-0.2.3.dist-info/LICENSE
brei-0.2.3.dist-info/METADATA
brei-0.2.3.dist-info/WHEEL
brei-0.2.3.dist-info/entry_points.txt
brei-0.2.3.dist-info/RECORD
